__init__.py
nechestniy_znak/__init__.py
nechestniy_znak/crpt.py
nechestniy_znak/egais.py
nechestniy_znak-1.0.3.dist-info/LICENSE
nechestniy_znak-1.0.3.dist-info/METADATA
nechestniy_znak-1.0.3.dist-info/WHEEL
nechestniy_znak-1.0.3.dist-info/top_level.txt
nechestniy_znak-1.0.3.dist-info/RECORD
