Metadata-Version: 2.1
Name: nechestniy_znak
Version: 1.0.3
Summary: Библеотека обертка для API ГИС МТ “Честный Знак”
Author-email: li0ard <li0ard@proton.me>
Maintainer-email: li0ard <li0ard@proton.me>
Project-URL: Homepage, https://github.com/li0ard/nechestniy_znak
Project-URL: Issues, https://github.com/li0ard/nechestniy_znak/issues
Classifier: Development Status :: 4 - Beta
Classifier: Programming Language :: Python :: 3.8
Classifier: License :: OSI Approved :: MIT License
Classifier: Operating System :: OS Independent
Requires-Python: >=3.8
License-File: LICENSE
Requires-Dist: requests
